alert_helper/__init__.py
alert_helper/alert.py
alert_helper/app/__init__.py
alert_helper/app/base.py
alert_helper/app/slack.py
alert_helper/cli.py
alert_helper/types.py
alert_helper-0.1.8.dist-info/WHEEL
alert_helper-0.1.8.dist-info/entry_points.txt
alert_helper-0.1.8.dist-info/METADATA
alert_helper-0.1.8.dist-info/RECORD
