Metadata-Version: 2.3
Name: alert-helper
Version: 0.1.8
Summary: Simple python notification helper.
Author: richardSHkim
Author-email: richardSHkim <kshtrue95@gmail.com>
Requires-Dist: requests>=2.32.5
Requires-Python: >=3.11
Project-URL: Homepage, https://github.com/richardSHkim/alert-helper
